beout/__init__.py
beout/terminal.py
beout-0.1.1.dist-info/DESCRIPTION.rst
beout-0.1.1.dist-info/METADATA
beout-0.1.1.dist-info/RECORD
beout-0.1.1.dist-info/WHEEL
beout-0.1.1.dist-info/metadata.json
beout-0.1.1.dist-info/top_level.txt
