Metadata-Version: 2.0
Name: beout
Version: 0.1.1
Summary: beout  is a library for easily generating beautiful output for long-running processes
Home-page: https://github.com/abesto/beout
Author: Zoltan Nagy
Author-email: zoltan.nagy@prezi.com
License: MIT
Keywords: terminal
Platform: any
Classifier: Development Status :: 4 - Beta
Classifier: Environment :: Console
Classifier: Intended Audience :: Developers
Classifier: License :: OSI Approved :: MIT License
Classifier: Operating System :: OS Independent
Classifier: Programming Language :: Python
Classifier: Programming Language :: Python :: 2
Classifier: Programming Language :: Python :: 2.6
Classifier: Programming Language :: Python :: 2.7
Classifier: Topic :: Software Development :: Libraries :: Python Modules
Requires-Dist: humanize
Requires-Dist: termcolor
